baseline/__init__.py
baseline/classification.py
baseline/data.py
baseline/pipeline.py
baseline/regression.py
base2lines-0.0.16.dist-info/LICENSE
base2lines-0.0.16.dist-info/METADATA
base2lines-0.0.16.dist-info/WHEEL
base2lines-0.0.16.dist-info/top_level.txt
base2lines-0.0.16.dist-info/RECORD
