Metadata-Version: 2.1
Name: base2lines
Version: 0.0.16
Summary: a python package to benchmarks algorithms against various datasets
Home-page: UNKNOWN
Author: Vishwas
Author-email: vishwasgoyal47@gmail.com
License: UNKNOWN
Platform: UNKNOWN
Classifier: Development Status :: 1 - Planning
Classifier: Intended Audience :: Developers
Classifier: Programming Language :: Python :: 3
Classifier: Operating System :: Unix
Classifier: Operating System :: MacOS :: MacOS X
Classifier: Operating System :: Microsoft :: Windows
License-File: LICENSE
Requires-Dist: seaborn
Requires-Dist: scikit-learn
Requires-Dist: xgboost
